{"name":"EXMO","currencies":[{"name":"ETH","fullName":"Ethereum"},{"name":"ROOBEE","fullName":"ROOBEE"},{"name":"ALGO","fullName":"Algorand"},{"name":"TON","fullName":"Toncoin"},{"name":"BTC","fullName":"Bitcoin"},{"name":"USDT","fullName":"Tether"},{"name":"ADA","fullName":"Cardano"},{"name":"CRON","fullName":"Cryptocean"},{"name":"DEBT","fullName":"The Debt Box"},{"name":"XRP","fullName":"XRP"},{"name":"GMT","fullName":"GMT Token"},{"name":"BCH","fullName":"Bitcoin Cash"},{"name":"DASH","fullName":"Dash"},{"name":"USDC","fullName":"USD Coin"},{"name":"PRQ","fullName":"PARSIQ"},{"name":"UNI","fullName":"Uniswap"},{"name":"IQN","fullName":"IQeon"},{"name":"SOL","fullName":"Solana"},{"name":"EXM","fullName":"EXMO Coin"},{"name":"NEAR","fullName":"NEAR Protocol"},{"name":"DOT","fullName":"Polkadot"},{"name":"ETC","fullName":"Ethereum Classic"},{"name":"WXT","fullName":"Wirex Token"},{"name":"SHIB","fullName":"Shiba Inu"}]}