{"name":"FTX","currencies":[{"name":"NEAR","fullName":"NEAR Protocol"},{"name":"BEAR","fullName":"3X Short Bitcoin Token"},{"name":"ETHBULL","fullName":"3X Long Ethereum Token"},{"name":"DOT","fullName":"Polkadot"},{"name":"BTC","fullName":"Bitcoin"},{"name":"USTC","fullName":"TerraClassicUSD"},{"name":"ETH","fullName":"Ethereum"},{"name":"BNB","fullName":"BNB"},{"name":"ATOM","fullName":"Cosmos"},{"name":"UNI","fullName":"Uniswap"},{"name":"SRM","fullName":"Serum"},{"name":"USDT","fullName":"Tether"},{"name":"UBXT","fullName":"UpBots"},{"name":"CTX","fullName":"C2X"},{"name":"DAI","fullName":"Dai"},{"name":"KNC","fullName":"Kyber Network Crystal v2"},{"name":"HNT","fullName":"Helium"},{"name":"LUNC","fullName":"Terra Classic"},{"name":"FIDA","fullName":"Bonfida"},{"name":"COMP","fullName":"Compound"},{"name":"MOB","fullName":"MobileCoin"},{"name":"SOL","fullName":"Solana"},{"name":"SUSHI","fullName":"SushiSwap"},{"name":"XRP","fullName":"XRP"},{"name":"CHZ","fullName":"Chiliz"},{"name":"AMPL","fullName":"Ampleforth"},{"name":"AAVE","fullName":"Aave"},{"name":"BRZ","fullName":"Brazilian Digital Token"},{"name":"BAL","fullName":"Balancer"},{"name":"FTT","fullName":"FTX Token"},{"name":"LTC","fullName":"Litecoin"},{"name":"TRX","fullName":"TRON"},{"name":"DOGE","fullName":"Dogecoin"},{"name":"AVAX","fullName":"Avalanche"},{"name":"BNBBULL","fullName":"3X Long BNB Token"},{"name":"MKR","fullName":"Maker"},{"name":"YFI","fullName":"yearn.finance"},{"name":"RUNE","fullName":"THORChain"},{"name":"ALGO","fullName":"Algorand"},{"name":"AUDIO","fullName":"Audius"},{"name":"LINK","fullName":"Chainlink"},{"name":"BULL","fullName":"3X Long Bitcoin Token"},{"name":"TOMO","fullName":"TomoChain"},{"name":"BCH","fullName":"Bitcoin Cash"},{"name":"XAUT","fullName":"Tether Gold"},{"name":"GST","fullName":"Green Satoshi Token (SOL)"},{"name":"MATH","fullName":"MATH"},{"name":"CREAM","fullName":"Cream Finance"},{"name":"XRPBULL","fullName":"3x Long XRP Token"},{"name":"BCHBEAR","fullName":"3x Short Bitcoin Cash Token"},{"name":"SXP","fullName":"SXP"},{"name":"DEFIBULL","fullName":"3X Long DeFi Index Token"},{"name":"ETHBEAR","fullName":"3X Short Ethereum Token"},{"name":"EURT","fullName":"Tether EURt"},{"name":"LTCBEAR","fullName":"3x Short Litecoin Token"},{"name":"AKRO","fullName":"Akropolis"},{"name":"LTCBULL","fullName":"3x Long Litecoin Token"},{"name":"VETBULL","fullName":"3X Long VeChain Token"},{"name":"OXY","fullName":"Oxygen"},{"name":"DMG","fullName":"DMM: Governance"},{"name":"CUSDT","fullName":"Compound USDT"},{"name":"BCHBULL","fullName":"3x Long Bitcoin Cash Token"},{"name":"LINKBULL","fullName":"3X Long Chainlink Token"},{"name":"EOSBULL","fullName":"3x Long EOS Token"},{"name":"LUA","fullName":"LuaSwap"},{"name":"XTZBULL","fullName":"3x Long Tezos Token"},{"name":"XRPBEAR","fullName":"3x Short XRP Token"},{"name":"BSVBEAR","fullName":"3x Short Bitcoin SV Token"},{"name":"PAXG","fullName":"PAX Gold"},{"name":"BSVBULL","fullName":"3x Long Bitcoin SV Token"},{"name":"HGET","fullName":"Hedget"},{"name":"ROOK","fullName":"Rook"},{"name":"IBVOL","fullName":"Inverse Bitcoin Volatility Token"},{"name":"TRU","fullName":"TrueFi"},{"name":"BVOL","fullName":"1x Long Bitcoin Implied Volatility Token"},{"name":"MAPS","fullName":"MAPS"},{"name":"EOSBEAR","fullName":"3x Short EOS Token"},{"name":"MTA","fullName":"mStable Governance Token: Meta (MTA)"},{"name":"WRX","fullName":"WazirX"},{"name":"HXRO","fullName":"Hxro"},{"name":"LINKBEAR","fullName":"3X Short Chainlink Token"},{"name":"FRONT","fullName":"Frontier"},{"name":"XTZBEAR","fullName":"3x Short Tezos Token"}]}